inmanta_plugins/apt/__init__.py
inmanta_plugins/apt/setup.cfg
inmanta_plugins/apt/model/_init.cf
inmanta_plugins/apt/templates/repo.tmpl
inmanta_module_apt-0.4.26.dist-info/METADATA
inmanta_module_apt-0.4.26.dist-info/WHEEL
inmanta_module_apt-0.4.26.dist-info/top_level.txt
inmanta_module_apt-0.4.26.dist-info/RECORD
