Metadata-Version: 2.1
Name: inmanta-module-apt
Version: 0.4.26
License: Apache 2.0
Requires-Dist: inmanta-module-std
